{
 "name": "稲荷崎-六名軸",
 "school": "稲荷崎",
 "source": "decks/稲荷崎/六名軸.csv",
 "cards": [
  {
   "id": "HV-P01-063",
   "count": 3
  },
  {
   "id": "HV-P02-016",
   "count": 3
  },
  {
   "id": "HV-P02-017",
   "count": 1
  },
  {
   "id": "HV-P02-020",
   "count": 3
  },
  {
   "id": "HV-P02-022",
   "count": 3
  },
  {
   "id": "HV-P02-077",
   "count": 4
  },
  {
   "id": "HV-P02-027",
   "count": 3
  },
  {
   "id": "HV-P02-034",
   "count": 5
  },
  {
   "id": "HV-P02-024",
   "count": 2
  },
  {
   "id": "HV-P01-065",
   "count": 1
  },
  {
   "id": "HV-P02-035",
   "count": 2
  },
  {
   "id": "HV-P02-003",
   "count": 2
  },
  {
   "id": "HV-P02-085",
   "count": 2
  },
  {
   "id": "HV-P02-087",
   "count": 2
  },
  {
   "id": "HV-D03-013",
   "count": 3
  },
  {
   "id": "HV-P02-089",
   "count": 1
  }
 ]
}